tests/__init__.py
vdoxa/__init__.py
vdoxa/parser.py
vdoxa/trim_parser.py
vdoxa/cli/__init__.py
vdoxa/cli/arguments.py
vdoxa/cli/formatter.py
vdoxa/cli/options.py
vdoxa/cli/strings.py
vdoxa/core/__init__.py
vdoxa/core/trim.py
vdoxa/utils/__init__.py
vdoxa/utils/common.py
vdoxa/utils/file_ops.py
vdoxa/utils/opencv.py
vdoxa/utils/options.py
vdoxa/vars/__init__.py
vdoxa/vars/cmd.py
vdoxa/vars/colors.py
vdoxa/vars/dev.py
vdoxa-0.2.dist-info/LICENSE
vdoxa-0.2.dist-info/METADATA
vdoxa-0.2.dist-info/WHEEL
vdoxa-0.2.dist-info/entry_points.txt
vdoxa-0.2.dist-info/top_level.txt
vdoxa-0.2.dist-info/RECORD
