Metadata-Version: 2.1
Name: vdoxa
Version: 0.2
Summary: vdoXA is an open-source python package for trimming the videos.
Home-page: https://github.com/xames3/vdoxa/
Author: XAMES3
Author-email: xames3.developer@gmail.com
Maintainer: XAMES3
Maintainer-email: xames3.developer@gmail.com
License: Apache 2.0
Download-URL: https://github.com/xames3/vdoxa/
Keywords: opencv2 cv2 moviepy
Platform: UNKNOWN
Classifier: Intended Audience :: Developers
Classifier: Intended Audience :: End Users/Desktop
Classifier: Intended Audience :: Information Technology
Classifier: Intended Audience :: Science/Research
Classifier: License :: OSI Approved :: Apache Software License
Classifier: Natural Language :: English
Requires-Python: ~=3.6
Requires-Dist: opencv-contrib-python
Requires-Dist: imutils
Requires-Dist: moviepy
Requires-Dist: questionary
